tests/__init__.py
tests/__init__.pyc
tests/ani_test.py
tests/arc_test.py
tests/arc_test.pyc
tests/cif_test.py
tests/cif_test.pyc
tests/incar_test.py
tests/incar_test.pyc
tests/oszicar_test.py
tests/oszicar_test.pyc
tests/out.log
tests/outcar_test.py
tests/outcar_test.pyc
tests/poscar_test.py
tests/poscar_test.pyc
tests/vaspy_test.py
tests/xdatcar_test.py
tests/xsd_test.py
tests/xsd_test.pyc
tests/xtd_test.py
tests/xtd_test.pyc
tests/xyzfile_test.py
tests/xyzfile_test.pyc
tests/__pycache__/__init__.cpython-35.pyc
tests/__pycache__/ani_test.cpython-35.pyc
tests/__pycache__/arc_test.cpython-35.pyc
tests/__pycache__/cif_test.cpython-35.pyc
tests/__pycache__/incar_test.cpython-35.pyc
tests/__pycache__/oszicar_test.cpython-35.pyc
tests/__pycache__/outcar_test.cpython-35.pyc
tests/__pycache__/poscar_test.cpython-35.pyc
tests/__pycache__/xdatcar_test.cpython-35.pyc
tests/__pycache__/xsd_test.cpython-35.pyc
tests/__pycache__/xtd_test.cpython-35.pyc
tests/__pycache__/xyzfile_test.cpython-35.pyc
tests/testdata/00-04.arc
tests/testdata/00-04.xtd
tests/testdata/CONTCAR
tests/testdata/DOS_SUM
tests/testdata/ELFCAR
tests/testdata/INCAR
tests/testdata/INCAR2
tests/testdata/KPOINTS
tests/testdata/OSZICAR
tests/testdata/OSZICAR_md
tests/testdata/OUT.ANI
tests/testdata/OUTCAR
tests/testdata/OUTCAR_freq
tests/testdata/PLOTCON
tests/testdata/POSCAR
tests/testdata/POSCAR_freq
tests/testdata/POTCAR
tests/testdata/XDATCAR
tests/testdata/bulk.xsd
tests/testdata/ceo2-111.cif
tests/testdata/fort.188
tests/testdata/h_top_c_fcc_far.xsd
tests/testdata/h_top_c_fcc_far_noname.xsd
tests/testdata/ts.xyz
tests/testdata/vasp.script
vaspy/__init__.py
vaspy/atomco.py
vaspy/electro.py
vaspy/elements.py
vaspy/errors.py
vaspy/functions.py
vaspy/incar.py
vaspy/iter.py
vaspy/matstudio.py
vaspy/plotter.py
vaspy/tests/__init__.py
vaspy/tests/ani_test.py
vaspy/tests/arc_test.py
vaspy/tests/cif_test.py
vaspy/tests/incar_test.py
vaspy-0.8.12.dist-info/DESCRIPTION.rst
vaspy-0.8.12.dist-info/METADATA
vaspy-0.8.12.dist-info/RECORD
vaspy-0.8.12.dist-info/WHEEL
vaspy-0.8.12.dist-info/metadata.json
vaspy-0.8.12.dist-info/top_level.txt
