Metadata-Version: 2.0
Name: vaspy
Version: 0.8.12
Summary: A pure Python library designed to make it easy and quick to manipulate VASP files
Home-page: https://github.com/PytLab/VASPy
Author: Shao-Zheng-Jiang
Author-email: shaozhengjiang@gmail.com
License: LICENSE
Platform: linux
Classifier: Development Status :: 3 - Alpha
Classifier: Topic :: Text Processing
Classifier: License :: OSI Approved :: MIT License
Classifier: Programming Language :: Python :: 2
Classifier: Programming Language :: Python :: 2.7
Classifier: Programming Language :: Python :: 3
Classifier: Programming Language :: Python :: 3.5
Requires-Dist: matplotlib (>=1.5.2)
Requires-Dist: numpy (>=1.11.1)
Requires-Dist: scipy (>=0.18.0)
